mcpmon/__init__.py
mcpmon/__main__.py
mcpmon/config.py
mcpmon/gateway.py
mcpmon/log.py
mcpmon-1.0.1.dist-info/METADATA
mcpmon-1.0.1.dist-info/WHEEL
mcpmon-1.0.1.dist-info/entry_points.txt
mcpmon-1.0.1.dist-info/RECORD
