Metadata-Version: 2.4
Name: mcpmon
Version: 1.0.1
Summary: Hot reload for MCP servers. Like nodemon, but for MCP.
Project-URL: Homepage, https://github.com/b17z/mcpmon
Author: be.nvy
License-Expression: MIT
Keywords: development,hot-reload,mcp,nodemon
Classifier: Development Status :: 3 - Alpha
Classifier: Environment :: Console
Classifier: Intended Audience :: Developers
Classifier: License :: OSI Approved :: MIT License
Classifier: Programming Language :: Python :: 3
Classifier: Programming Language :: Python :: 3.10
Classifier: Programming Language :: Python :: 3.11
Classifier: Programming Language :: Python :: 3.12
Requires-Python: >=3.10
Requires-Dist: pyyaml>=6.0
Requires-Dist: watchfiles>=0.20.0
Provides-Extra: dev
Requires-Dist: pytest-timeout>=2.0.0; extra == 'dev'
Requires-Dist: pytest>=7.0.0; extra == 'dev'
